private_values/__init__.py
private_values/auto.py
private_values/base.py
private_values/csv.py
private_values/derivatives.py
private_values/env.py
private_values/ini.py
private_values/json.py
private_values/static.py
private_values-0.6.1.dist-info/LICENSE
private_values-0.6.1.dist-info/METADATA
private_values-0.6.1.dist-info/WHEEL
private_values-0.6.1.dist-info/top_level.txt
private_values-0.6.1.dist-info/RECORD
